{
    "0": {
        "head top": {
            "x": 585,
            "y": 353
        },
        "left elbow": {
            "x": 749,
            "y": 709
        },
        "right elbow": {
            "x": 379,
            "y": 685
        },
        "left wrist": {
            "x": 626,
            "y": 573
        },
        "right wrist": {
            "x": 538,
            "y": 595
        },
        "left knee": {
            "x": 790,
            "y": 1293
        },
        "right knee": {
            "x": 434,
            "y": 1336
        },
        "left ankle": {
            "x": 780,
            "y": 1522
        },
        "right ankle": {
            "x": 473,
            "y": 1550
        }
    }
}